Workbook

Sheet Despesas
B1: 2023 | N1: 2024
B2: JAN | C2: FEV | D2: MAR | E2: ABR | F2: MAI | G2: JUN | H2: JUL | I2: AGO | J2: SET | K2: OUT | L2: NOV | M2: DEZ | N2: JAN | O2: FEV | P2: MAR | Q2: ABR | R2: MAI | S2: JUN | T2: JUL | U2: AGO | V2: SET | W2: OUT | X2: NOV | Y2: DEZ
A3: Receitas | B3: =SUM(B4:B5) -> 3000 | C3: =SUM(C4:C5) -> 3300 | D3: =SUM(D4:D5) -> 3500 | E3: =SUM(E4:E5) -> 3000 | F3: =SUM(F4:F5) -> 3000 | G3: =SUM(G4:G5) -> 3400 | H3: =SUM(H4:H5) -> 3000 | I3: =SUM(I4:I5) -> 3600 | ... Y3: =SUM(Y4:Y5) -> 4000
A4: Salário | B4: 3000 | C4: 3000 | D4: 3000 | E4: 3000 | F4: 3000 | G4: 3000 | H4: 3000 | I4: 3000 | J4: 3000 | K4: 3000 | L4: 3000 | M4: 3000 | N4: 3500 | O4: 3500 | P4: 3500 | Q4: 3500 | R4: 3500 | S4: 3500 | T4: 3500 | U4: 3500 | V4: 3500 | W4: 3500 | X4: 3500 | Y4: 3500
A5: Outros | C5: 300 | D5: 500 | G5: 400 | I5: 600 | L5: 200 | M5: 500 | O5: 300 | P5: 500 | S5: 400 | U5: 600 | X5: 200 | Y5: 500
A6: Despesas Fixas | B6: =SUM(B7:B13) -> 1370 | C6: =SUM(C7:C13) -> 1370 | D6: =SUM(D7:D13) -> 1370 | E6: =SUM(E7:E13) -> 1370 | F6: =SUM(F7:F13) -> 1370 | G6: =SUM(G7:G13) -> 1370 | H6: =SUM(H7:H13) -> 1370 | I6: =SUM(I7:I13) -> 1370 | ... Y6: =SUM(Y7:Y13) -> 1370
A7: Aluguel | B7: 1000 | C7: 1000 | D7: 1000 | E7: 1000 | F7: 1000 | G7: 1000 | H7: 1000 | I7: 1000 | J7: 1000 | K7: 1000 | L7: 1000 | M7: 1000 | N7: 1000 | O7: 1000 | P7: 1000 | Q7: 1000 | R7: 1000 | S7: 1000 | T7: 1000 | U7: 1000 | V7: 1000 | W7: 1000 | X7: 1000 | Y7: 1000
A8: Carro
A9: Seguros | B9: 150 | C9: 150 | D9: 150 | E9: 150 | F9: 150 | G9: 150 | H9: 150 | I9: 150 | J9: 150 | K9: 150 | L9: 150 | M9: 150 | N9: 150 | O9: 150 | P9: 150 | Q9: 150 | R9: 150 | S9: 150 | T9: 150 | U9: 150 | V9: 150 | W9: 150 | X9: 150 | Y9: 150
A10: Educação
A11: Internet | B11: 100 | C11: 100 | D11: 100 | E11: 100 | F11: 100 | G11: 100 | H11: 100 | I11: 100 | J11: 100 | K11: 100 | L11: 100 | M11: 100 | N11: 100 | O11: 100 | P11: 100 | Q11: 100 | R11: 100 | S11: 100 | T11: 100 | U11: 100 | V11: 100 | W11: 100 | X11: 100 | Y11: 100
A12: TV a cabo | B12: 50 | C12: 50 | D12: 50 | E12: 50 | F12: 50 | G12: 50 | H12: 50 | I12: 50 | J12: 50 | K12: 50 | L12: 50 | M12: 50 | N12: 50 | O12: 50 | P12: 50 | Q12: 50 | R12: 50 | S12: 50 | T12: 50 | U12: 50 | V12: 50 | W12: 50 | X12: 50 | Y12: 50
A13: Impostos | B13: 70 | C13: 70 | D13: 70 | E13: 70 | F13: 70 | G13: 70 | H13: 70 | I13: 70 | J13: 70 | K13: 70 | L13: 70 | M13: 70 | N13: 70 | O13: 70 | P13: 70 | Q13: 70 | R13: 70 | S13: 70 | T13: 70 | U13: 70 | V13: 70 | W13: 70 | X13: 70 | Y13: 70
A14: Despesas Variáveis | B14: =SUM(B15:B23) -> 1012 | C14: =SUM(C15:C23) -> 1471 | D14: =SUM(D15:D23) -> 1287 | E14: =SUM(E15:E23) -> 1170 | F14: =SUM(F15:F23) -> 1621 | G14: =SUM(G15:G23) -> 1270 | H14: =SUM(H15:H23) -> 1268 | I14: =SUM(I15:I23) -> 1235 | ... Y14: =SUM(Y15:Y23) -> 1209
A15: Telefone | B15: 45 | C15: 41 | D15: 43 | E15: 42 | F15: 43 | G15: 42 | H15: 43 | I15: 43 | J15: 44 | K15: 40 | L15: 41 | M15: 42 | N15: 42 | O15: 42 | P15: 41 | Q15: 42 | R15: 45 | S15: 43 | T15: 44 | U15: 41 | V15: 41 | W15: 44 | X15: 40 | Y15: 42
A16: Luz | B16: 122 | C16: 261 | D16: 229 | E16: 252 | F16: 263 | G16: 237 | H16: 195 | I16: 290 | J16: 231 | K16: 139 | L16: 205 | M16: 194 | N16: 255 | O16: 228 | P16: 247 | Q16: 182 | R16: 242 | S16: 132 | T16: 188 | U16: 211 | V16: 225 | W16: 228 | X16: 276 | Y16: 125
A17: Água | B17: 54 | C17: 73 | D17: 42 | E17: 47 | F17: 53 | G17: 71 | H17: 79 | I17: 59 | J17: 43 | K17: 69 | L17: 67 | M17: 56 | N17: 44 | O17: 56 | P17: 61 | Q17: 49 | R17: 70 | S17: 76 | T17: 61 | U17: 46 | V17: 53 | W17: 43 | X17: 45 | Y17: 57
A18: Condomínio | B18: 305 | C18: 320 | D18: 313 | E18: 303 | F18: 329 | G18: 313 | H18: 358 | I18: 356 | J18: 333 | K18: 397 | L18: 344 | M18: 389 | N18: 369 | O18: 388 | P18: 311 | Q18: 381 | R18: 382 | S18: 394 | T18: 338 | U18: 385 | V18: 335 | W18: 340 | X18: 375 | Y18: 385
A19: Mercado | B19: 404 | C19: 405 | D19: 440 | E19: 429 | F19: 420 | G19: 477 | H19: 455 | I19: 434 | J19: 421 | K19: 475 | L19: 461 | M19: 499 | N19: 434 | O19: 445 | P19: 497 | Q19: 410 | R19: 465 | S19: 417 | T19: 413 | U19: 498 | V19: 464 | W19: 493 | X19: 454 | Y19: 500
A20: Vestuário | D20: 100 | G20: 50 | J20: 60 | M20: 100 | N20: 200 | P20: 50 | S20: 60 | U20: 70 | W20: 100
A21: Itens Casa | C21: 300 | K21: 200 | R21: 150 | W21: 200
A22: Transporte | B22: 82 | C22: 71 | D22: 120 | E22: 97 | F22: 113 | G22: 80 | H22: 138 | I22: 53 | J22: 96 | K22: 70 | L22: 138 | M22: 93 | N22: 77 | O22: 119 | P22: 114 | Q22: 85 | R22: 147 | S22: 120 | T22: 111 | U22: 115 | V22: 65 | W22: 70 | X22: 56 | Y22: 100
A23: Saúde | F23: 400 | O23: 200 | T23: 300
A24: Economias | B24: =SUM(B25:B26) -> 200 | C24: =SUM(C25:C26) -> 700 | D24: =SUM(D25:D26) -> 200 | E24: =SUM(E25:E26) -> 700 | F24: =SUM(F25:F26) -> 200 | G24: =SUM(G25:G26) -> 200 | H24: =SUM(H25:H26) -> 1200 | I24: =SUM(I25:I26) -> 200 | ... Y24: =SUM(Y25:Y26) -> 700
A25: Investimentos | C25: 500 | E25: 500 | H25: 1000 | J25: 500 | L25: 500 | N25: 1000 | P25: 2000 | R25: 1500 | T25: 1500 | V25: 1500 | X25: 1500 | Y25: 500
A26: Previdência | B26: 200 | C26: 200 | D26: 200 | E26: 200 | F26: 200 | G26: 200 | H26: 200 | I26: 200 | J26: 200 | K26: 200 | L26: 200 | M26: 200 | N26: 200 | O26: 200 | P26: 200 | Q26: 200 | R26: 200 | S26: 200 | T26: 200 | U26: 200 | V26: 200 | W26: 200 | X26: 200 | Y26: 200
A27: Fluxo de Caixa | B27: =B3-B6-B14-B24 -> 418 | C27: =C3-C6-C14-C24 -> -241 | D27: =D3-D6-D14-D24 -> 643 | E27: =E3-E6-E14-E24 -> -240 | F27: =F3-F6-F14-F24 -> -191 | G27: =G3-G6-G14-G24 -> 560 | H27: =H3-H6-H14-H24 -> -838 | I27: =I3-I6-I14-I24 -> 795 | ... Y27: =Y3-Y6-Y14-Y24 -> 721
A28: Fluxo Acumulado | B28: =B27 -> 418 | C28: =B28+C27 -> 177 | D28: =C28+D27 -> 820 | E28: =D28+E27 -> 580 | F28: =E28+F27 -> 389 | G28: =F28+G27 -> 949 | H28: =G28+H27 -> 111 | I28: =H28+I27 -> 906 | J28: =I28+J27 -> 608 | ... Y28: =X28+Y27 -> 1150
A35: JAN | B35: 2022
A36: FEV | B36: 2023
A37: MAR
A38: ABR
A39: MAI
A40: JUN
A41: JUL
A42: AGO
A43: SET
A44: OUT
A45: NOV
A46: DEZ

Sheet Cálculos
D1: Fixas | E1: =OFFSET(Despesas!A6,0,Cálculos!$B$7) -> 1370
D2: Variáveis | E2: =OFFSET(Despesas!A14,0,Cálculos!$B$7) -> 1471
A3: 2 | B3: {=INDEX(Despesas!A35:A46,Cálculos!A3)} -> FEV
D4: Despesas Fixas | E4: Aluguel | F4: =OFFSET(Despesas!A7,0,Cálculos!$B$7) -> 1000
D5: Despesas Fixas | E5: Carro | F5: =OFFSET(Despesas!A8,0,Cálculos!$B$7) -> 0
A6: 1 | B6: =IF(A6=1,0,12) -> 0 | C6: =IF(A6=1,2022,2023) -> 2022 | D6: Despesas Fixas | E6: Seguros | F6: =OFFSET(Despesas!A9,0,Cálculos!$B$7) -> 150
B7: =B6+A3 -> 2 | D7: Despesas Fixas | E7: Educação | F7: =OFFSET(Despesas!A10,0,Cálculos!$B$7) -> 0
D8: Despesas Fixas | E8: Internet | F8: =OFFSET(Despesas!A11,0,Cálculos!$B$7) -> 100
A9: ="Despesas "&B3&" "&C6 -> Despesas FEV 2022 | D9: Despesas Fixas | E9: TV a cabo | F9: =OFFSET(Despesas!A12,0,Cálculos!$B$7) -> 50
D10: Despesas Fixas | E10: Impostos | F10: =OFFSET(Despesas!A13,0,Cálculos!$B$7) -> 70
D11: Despesas Variáveis | E11: Telefone | F11: =OFFSET(Despesas!A15,0,Cálculos!$B$7) -> 41
D12: Despesas Variáveis | E12: Luz | F12: =OFFSET(Despesas!A16,0,Cálculos!$B$7) -> 261
D13: Despesas Variáveis | E13: Água | F13: =OFFSET(Despesas!A17,0,Cálculos!$B$7) -> 73
D14: Despesas Variáveis | E14: Condomínio | F14: =OFFSET(Despesas!A18,0,Cálculos!$B$7) -> 320
D15: Despesas Variáveis | E15: Mercado | F15: =OFFSET(Despesas!A19,0,Cálculos!$B$7) -> 405
D16: Despesas Variáveis | E16: Vestuário | F16: =OFFSET(Despesas!A20,0,Cálculos!$B$7) -> 0
D17: Despesas Variáveis | E17: Itens Casa | F17: =OFFSET(Despesas!A21,0,Cálculos!$B$7) -> 300
D18: Despesas Variáveis | E18: Transporte | F18: =OFFSET(Despesas!A22,0,Cálculos!$B$7) -> 71
D19: Despesas Variáveis | E19: Saúde | F19: =OFFSET(Despesas!A23,0,Cálculos!$B$7) -> 0

Sheet Dashboard
R3: 8
R6: 1
