Workbook

Sheet Funcionários
B1: Cadastro de Funcionários
B3: Funcionário | C3: Cargo | D3: Departamento | E3: Salário Bruto | F3: Regime Contratação | G3: Valor Hora Extra
B4: Roberta Alencar | C4: Diretor | D4: Operações | E4: 20000 | F4: PJ | G4: =IF(Tabela1[[#This Row],[Regime Contratação]]="CLT",Tabela1[[#This Row],[Salário Bruto]]*1.5/220,0) -> 0
B5: Felipe Mascarenhas | C5: Coordenador | D5: Finanças | E5: 8000 | F5: CLT | G5: =IF(Tabela1[[#This Row],[Regime Contratação]]="CLT",Tabela1[[#This Row],[Salário Bruto]]*1.5/220,0) -> 54.545455
B6: Eliza Luna | C6: Especialista | D6: Logística | E6: 6500 | F6: CLT | G6: =IF(Tabela1[[#This Row],[Regime Contratação]]="CLT",Tabela1[[#This Row],[Salário Bruto]]*1.5/220,0) -> 44.318182
B7: Eduardo Damasceno | C7: Analista Sênior | D7: Recursos Humanos | E7: 4000 | F7: CLT | G7: =IF(Tabela1[[#This Row],[Regime Contratação]]="CLT",Tabela1[[#This Row],[Salário Bruto]]*1.5/220,0) -> 27.272727
B8: Bruna Sales | C8: Analista | D8: Marketing | E8: 3000 | F8: CLT | G8: =IF(Tabela1[[#This Row],[Regime Contratação]]="CLT",Tabela1[[#This Row],[Salário Bruto]]*1.5/220,0) -> 20.454545
B9: Lucas Pinheiro | C9: Estagiário | D9: Operações | E9: 2000 | F9: Estágio | G9: =IF(Tabela1[[#This Row],[Regime Contratação]]="CLT",Tabela1[[#This Row],[Salário Bruto]]*1.5/220,0) -> 0
B10: Bento Luiz | C10: Jovem Aprendiz | D10: Finanças | E10: 1000 | F10: Jovem Aprendiz | G10: =IF(Tabela1[[#This Row],[Regime Contratação]]="CLT",Tabela1[[#This Row],[Salário Bruto]]*1.5/220,0) -> 0
B11: Diego Diegues | C11: Analista Sênior | D11: Logística | E11: 2000 | F11: CLT | G11: =IF(Tabela1[[#This Row],[Regime Contratação]]="CLT",Tabela1[[#This Row],[Salário Bruto]]*1.5/220,0) -> 13.636364

Sheet Folha
B1: Folha de Pagamentos
B3: Funcionário | C3: Competência | D3: Data pagamento | E3: Quantidade HE | F3: Salário Bruto | G3: Desconto Transporte | H3: Desconto IR | I3: Desconto INSS | J3: Outros Descontos | K3: Valor Hora Extra | L3: Salário Líquido
B4: Roberta Alencar | C4: 45292 | D4: 45323 | E4: 0 | F4: =VLOOKUP(Tabela2[[#This Row],[Funcionário]],Funcionários!B:G,4,0) -> 20000 | G4: 300 | H4: 2400 | I4: 1800 | J4: 113 | K4: =Tabela2[[#This Row],[Quantidade HE]]*VLOOKUP(Tabela2[[#This Row],[Funcionário]],Funcionários!B:G,6,0) -> 0 | L4: =Tabela2[[#This Row],[Salário Bruto]]-SUM(Tabela2[[#This Row],[Desconto Transporte]:[Outros Descontos]])+Tabela2[[#This Row],[Valor Hora Extra]] -> 15387
B5: Felipe Mascarenhas | C5: 45292 | D5: 45323 | E5: 0 | F5: =VLOOKUP(Tabela2[[#This Row],[Funcionário]],Funcionários!B:G,4,0) -> 8000 | G5: 480 | H5: 880 | I5: 800 | J5: 162 | K5: =Tabela2[[#This Row],[Quantidade HE]]*VLOOKUP(Tabela2[[#This Row],[Funcionário]],Funcionários!B:G,6,0) -> 0 | L5: =Tabela2[[#This Row],[Salário Bruto]]-SUM(Tabela2[[#This Row],[Desconto Transporte]:[Outros Descontos]])+Tabela2[[#This Row],[Valor Hora Extra]] -> 5678
B6: Eliza Luna | C6: 45292 | D6: 45323 | E6: 3 | F6: =VLOOKUP(Tabela2[[#This Row],[Funcionário]],Funcionários!B:G,4,0) -> 6500 | G6: 325 | H6: 650 | I6: 650 | J6: 111 | K6: =Tabela2[[#This Row],[Quantidade HE]]*VLOOKUP(Tabela2[[#This Row],[Funcionário]],Funcionários!B:G,6,0) -> 132.95455 | L6: =Tabela2[[#This Row],[Salário Bruto]]-SUM(Tabela2[[#This Row],[Desconto Transporte]:[Outros Descontos]])+Tabela2[[#This Row],[Valor Hora Extra]] -> 4896.9545
B7: Eduardo Damasceno | C7: 45292 | D7: 45323 | E7: 3 | F7: =VLOOKUP(Tabela2[[#This Row],[Funcionário]],Funcionários!B:G,4,0) -> 4000 | G7: 280 | H7: 400 | I7: 280 | J7: 138 | K7: =Tabela2[[#This Row],[Quantidade HE]]*VLOOKUP(Tabela2[[#This Row],[Funcionário]],Funcionários!B:G,6,0) -> 81.818182 | L7: =Tabela2[[#This Row],[Salário Bruto]]-SUM(Tabela2[[#This Row],[Desconto Transporte]:[Outros Descontos]])+Tabela2[[#This Row],[Valor Hora Extra]] -> 2983.8182
B8: Bruna Sales | C8: 45292 | D8: 45323 | E8: 5 | F8: =VLOOKUP(Tabela2[[#This Row],[Funcionário]],Funcionários!B:G,4,0) -> 3000 | G8: 180 | H8: 330 | I8: 270 | J8: 127 | K8: =Tabela2[[#This Row],[Quantidade HE]]*VLOOKUP(Tabela2[[#This Row],[Funcionário]],Funcionários!B:G,6,0) -> 102.27273 | L8: =Tabela2[[#This Row],[Salário Bruto]]-SUM(Tabela2[[#This Row],[Desconto Transporte]:[Outros Descontos]])+Tabela2[[#This Row],[Valor Hora Extra]] -> 2195.2727
B9: Lucas Pinheiro | C9: 45292 | D9: 45323 | E9: 5 | F9: =VLOOKUP(Tabela2[[#This Row],[Funcionário]],Funcionários!B:G,4,0) -> 2000 | G9: 120 | H9: 200 | I9: 140 | J9: 141 | K9: =Tabela2[[#This Row],[Quantidade HE]]*VLOOKUP(Tabela2[[#This Row],[Funcionário]],Funcionários!B:G,6,0) -> 0 | L9: =Tabela2[[#This Row],[Salário Bruto]]-SUM(Tabela2[[#This Row],[Desconto Transporte]:[Outros Descontos]])+Tabela2[[#This Row],[Valor Hora Extra]] -> 1399
B10: Bento Luiz | C10: 45292 | D10: 45323 | E10: 6 | F10: =VLOOKUP(Tabela2[[#This Row],[Funcionário]],Funcionários!B:G,4,0) -> 1000 | G10: 70 | H10: 100 | I10: 60 | J10: 115 | K10: =Tabela2[[#This Row],[Quantidade HE]]*VLOOKUP(Tabela2[[#This Row],[Funcionário]],Funcionários!B:G,6,0) -> 0 | L10: =Tabela2[[#This Row],[Salário Bruto]]-SUM(Tabela2[[#This Row],[Desconto Transporte]:[Outros Descontos]])+Tabela2[[#This Row],[Valor Hora Extra]] -> 655
B11: Diego Diegues | C11: 45292 | D11: 45323 | E11: 3 | F11: =VLOOKUP(Tabela2[[#This Row],[Funcionário]],Funcionários!B:G,4,0) -> 2000 | G11: 120 | H11: 240 | I11: 120 | J11: 120 | K11: =Tabela2[[#This Row],[Quantidade HE]]*VLOOKUP(Tabela2[[#This Row],[Funcionário]],Funcionários!B:G,6,0) -> 40.909091 | L11: =Tabela2[[#This Row],[Salário Bruto]]-SUM(Tabela2[[#This Row],[Desconto Transporte]:[Outros Descontos]])+Tabela2[[#This Row],[Valor Hora Extra]] -> 1440.9091
B12: Roberta Alencar | C12: 45323 | D12: 45352 | E12: 7 | F12: =VLOOKUP(Tabela2[[#This Row],[Funcionário]],Funcionários!B:G,4,0) -> 20000 | G12: 400 | H12: 2400 | I12: 1400 | J12: 192 | K12: =Tabela2[[#This Row],[Quantidade HE]]*VLOOKUP(Tabela2[[#This Row],[Funcionário]],Funcionários!B:G,6,0) -> 0 | L12: =Tabela2[[#This Row],[Salário Bruto]]-SUM(Tabela2[[#This Row],[Desconto Transporte]:[Outros Descontos]])+Tabela2[[#This Row],[Valor Hora Extra]] -> 15608
B13: Felipe Mascarenhas | C13: 45323 | D13: 45352 | E13: 1 | F13: =VLOOKUP(Tabela2[[#This Row],[Funcionário]],Funcionários!B:G,4,0) -> 8000 | G13: 480 | H13: 960 | I13: 560 | J13: 168 | K13: =Tabela2[[#This Row],[Quantidade HE]]*VLOOKUP(Tabela2[[#This Row],[Funcionário]],Funcionários!B:G,6,0) -> 54.545455 | L13: =Tabela2[[#This Row],[Salário Bruto]]-SUM(Tabela2[[#This Row],[Desconto Transporte]:[Outros Descontos]])+Tabela2[[#This Row],[Valor Hora Extra]] -> 5886.5455
B14: Eliza Luna | C14: 45323 | D14: 45352 | E14: 6 | F14: =VLOOKUP(Tabela2[[#This Row],[Funcionário]],Funcionários!B:G,4,0) -> 6500 | G14: 390 | H14: 650 | I14: 455 | J14: 164 | K14: =Tabela2[[#This Row],[Quantidade HE]]*VLOOKUP(Tabela2[[#This Row],[Funcionário]],Funcionários!B:G,6,0) -> 265.90909 | L14: =Tabela2[[#This Row],[Salário Bruto]]-SUM(Tabela2[[#This Row],[Desconto Transporte]:[Outros Descontos]])+Tabela2[[#This Row],[Valor Hora Extra]] -> 5106.9091
B15: Eduardo Damasceno | C15: 45323 | D15: 45352 | E15: 2 | F15: =VLOOKUP(Tabela2[[#This Row],[Funcionário]],Funcionários!B:G,4,0) -> 4000 | G15: 240 | H15: 480 | I15: 400 | J15: 131 | K15: =Tabela2[[#This Row],[Quantidade HE]]*VLOOKUP(Tabela2[[#This Row],[Funcionário]],Funcionários!B:G,6,0) -> 54.545455 | L15: =Tabela2[[#This Row],[Salário Bruto]]-SUM(Tabela2[[#This Row],[Desconto Transporte]:[Outros Descontos]])+Tabela2[[#This Row],[Valor Hora Extra]] -> 2803.5455
... B99: Diego Diegues | C99: 45627 | D99: 45658 | E99: 3 | F99: =VLOOKUP(Tabela2[[#This Row],[Funcionário]],Funcionários!B:G,4,0) -> 2000 | G99: 100 | H99: 220 | I99: 200 | J99: 101 | K99: =Tabela2[[#This Row],[Quantidade HE]]*VLOOKUP(Tabela2[[#This Row],[Funcionário]],Funcionários!B:G,6,0) -> 40.909091 | L99: =Tabela2[[#This Row],[Salário Bruto]]-SUM(Tabela2[[#This Row],[Desconto Transporte]:[Outros Descontos]])+Tabela2[[#This Row],[Valor Hora Extra]] -> 1419.9091

Sheet Cálculos
A3: Rótulos de Linha | B3: Soma de Salário Líquido | D3: Rótulos de Linha | E3: Soma de Salário Líquido | G3: Rótulos de Linha | H3: Soma de Quantidade HE
A4: jan | B4: 34635.955 | D4: Bento Luiz | E4: 7171 | G4: Bruna Sales | H4: 37
A5: fev | B5: 35466.727 | D5: Bruna Sales | E5: 26387.818 | G5: Felipe Mascarenhas | H5: 37
A6: mar | B6: 33800.773 | D6: Diego Diegues | E6: 18370.364 | G6: Roberta Alencar | H6: 37
A7: abr | B7: 34780.955 | D7: Eduardo Damasceno | E7: 35028.273 | G7: Diego Diegues | H7: 43
A8: mai | B8: 35725.818 | D8: Eliza Luna | E8: 59238.5 | G8: Eduardo Damasceno | H8: 45
A9: jun | B9: 33388.591 | D9: Felipe Mascarenhas | E9: 70847.182 | G9: Bento Luiz | H9: 46
A10: jul | B10: 34837.909 | D10: Lucas Pinheiro | E10: 16240 | G10: Lucas Pinheiro | H10: 47
A11: ago | B11: 35736.227 | D11: Roberta Alencar | E11: 182514 | G11: Eliza Luna | H11: 55
A12: set | B12: 33570.045 | D12: Total Geral | E12: 415797.14 | G12: Total Geral | H12: 347
A13: out | B13: 34621.955
A14: nov | B14: 35308.682
A15: dez | B15: 33923.5
A16: Total Geral | B16: 415797.14
A25: Rótulos de Linha | B25: Soma de Desconto INSS | D25: Rótulos de Linha | E25: Soma de Desconto IR | G25: Rótulos de Linha | H25: Soma de Desconto Transporte | J25: Rótulos de Linha | K25: Soma de Total Descontos
A26: jan | B26: 4120 | D26: jan | E26: 5200 | G26: jan | H26: 1875 | J26: jan | K26: 12222
A27: fev | B27: 3285 | D27: fev | E27: 5160 | G27: fev | H27: 1950 | J27: fev | K27: 11606
A28: mar | B28: 4070 | D28: mar | E28: 5415 | G28: mar | H28: 2660 | J28: mar | K28: 13364
A29: abr | B29: 4120 | D29: abr | E29: 5200 | G29: abr | H29: 1875 | J29: abr | K29: 12452
A30: mai | B30: 3285 | D30: mai | E30: 5160 | G30: mai | H30: 1950 | J30: mai | K30: 11531
A31: jun | B31: 4070 | D31: jun | E31: 5415 | G31: jun | H31: 2660 | J31: jun | K31: 13408
A32: jul | B32: 4120 | D32: jul | E32: 5200 | G32: jul | H32: 1875 | J32: jul | K32: 12303
A33: ago | B33: 3285 | D33: ago | E33: 5160 | G33: ago | H33: 1950 | J33: ago | K33: 11524
A34: set | B34: 4070 | D34: set | E34: 5415 | G34: set | H34: 2660 | J34: set | K34: 13397
A35: out | B35: 4120 | D35: out | E35: 5200 | G35: out | H35: 1875 | J35: out | K35: 12461
A36: nov | B36: 3285 | D36: nov | E36: 5160 | G36: nov | H36: 1950 | J36: nov | K36: 11672
A37: dez | B37: 4070 | D37: dez | E37: 5415 | G37: dez | H37: 2660 | J37: dez | K37: 13289
A38: Total Geral | B38: 45900 | D38: Total Geral | E38: 63100 | G38: Total Geral | H38: 25940 | J38: Total Geral | K38: 149229

Sheet Painel
